ask_sdk_jinja_renderer/__init__.py
ask_sdk_jinja_renderer/__version__.py
ask_sdk_jinja_renderer/jinja_template_renderer.py
ask_sdk_jinja_renderer-1.0.0.dist-info/METADATA
ask_sdk_jinja_renderer-1.0.0.dist-info/WHEEL
ask_sdk_jinja_renderer-1.0.0.dist-info/top_level.txt
ask_sdk_jinja_renderer-1.0.0.dist-info/RECORD
