Metadata-Version: 2.1
Name: ask-sdk-jinja-renderer
Version: 1.0.0
Summary: ask-sdk-jinja-renderer is an SDK package for supporting template responses for skill developers, when built using ASK Python SDK. It provides jinja framework as a template engine to render the response loaded from the templateand inject the data passed and finally deserialize it toa custom response format
Home-page: https://github.com/alexa/alexa-skills-kit-sdk-for-python
Author: Alexa Skills Kit
Author-email: ask-sdk-dynamic@amazon.com
License: Apache 2.0
Keywords: ASK SDK,Alexa Skills Kit,Alexa
Platform: UNKNOWN
Classifier: Development Status :: 5 - Production/Stable
Classifier: Intended Audience :: Developers
Classifier: Natural Language :: English
Classifier: License :: OSI Approved :: Apache Software License
Classifier: Programming Language :: Python
Classifier: Programming Language :: Python :: 2
Classifier: Programming Language :: Python :: 2.7
Classifier: Programming Language :: Python :: 3
Classifier: Programming Language :: Python :: 3.6
Classifier: Programming Language :: Python :: 3.7
Requires-Python: >2.6, !=3.0.*, !=3.1.*, !=3.2.*, !=3.3.*, !=3.4.*, !=3.5.*
Requires-Dist: ask-sdk-core (>1.10.2)
Requires-Dist: jinja2 (>=2.10.1)
